onnxsharp/__init__.py
onnxsharp/basics.py
onnxsharp/command_line.py
onnxsharp/graph.py
onnxsharp/graph_folder.py
onnxsharp/graph_sort.py
onnxsharp/graph_utils.py
onnxsharp/model.py
onnxsharp/node.py
onnxsharp/npy_utils.py
onnxsharp/ort_utils.py
onnxsharp/tensor.py
onnxsharp/topy_sample.py
onnxsharp/torch_utils.py
onnxsharp/viz/__init__.py
onnxsharp/viz/main.py
onnxsharp/viz/sample.py
onnxsharp/viz/viz_gen.py
onnxsharp-0.1.1.data/scripts/onnx_summarize
onnxsharp-0.1.1.data/scripts/ort_get_peak_details
onnxsharp-0.1.1.data/scripts/ort_get_peak_op_summary
onnxsharp-0.1.1.data/scripts/ort_get_peak_step
onnxsharp-0.1.1.data/scripts/ort_get_peak_summary
onnxsharp-0.1.1.data/scripts/ort_parse_output_name
onnxsharp-0.1.1.data/scripts/ort_parse_peak_summary
onnxsharp-0.1.1.data/scripts/ort_scan_output_in_order
onnxsharp-0.1.1.dist-info/LICENSE
onnxsharp-0.1.1.dist-info/METADATA
onnxsharp-0.1.1.dist-info/WHEEL
onnxsharp-0.1.1.dist-info/entry_points.txt
onnxsharp-0.1.1.dist-info/top_level.txt
onnxsharp-0.1.1.dist-info/RECORD
